symphony/__init__.py
symphony/__main__.py
symphony/cli.py
symphony/config.py
symphony/errors.py
symphony/logging_config.py
symphony/runtime.py
symphony/version.py
symphony/conductor/__init__.py
symphony/conductor/app.py
symphony/conductor/common.py
symphony/conductor/deployment_assignment_registry.py
symphony/conductor/deployment_store.py
symphony/conductor/http_server.py
symphony/conductor/jobs.py
symphony/conductor/models.py
symphony/conductor/node_registry.py
symphony/conductor/scheduler.py
symphony/conductor/service.py
symphony/conductor/api/__init__.py
symphony/conductor/api/routes.py
symphony/conductor/api/server.py
symphony/conductor/ui/ui_router.py
symphony/conductor/ui/dist/favicon.ico
symphony/conductor/ui/dist/index.html
symphony/conductor/ui/dist/logo.svg
symphony/conductor/ui/dist/placeholder.svg
symphony/conductor/ui/dist/robots.txt
symphony/conductor/ui/dist/assets/index-BXO-ficb.css
symphony/conductor/ui/dist/assets/index-CYLZaKcZ.js
symphony/docs/architecture.md
symphony/docs/cli.md
symphony/docs/protocol.md
symphony/docs/images/ui-1.png
symphony/docs/images/ui-2.png
symphony/interface/sqlite.py
symphony/node/__init__.py
symphony/node/agent.py
symphony/node/app.py
symphony/node/job_store.py
symphony/node/runner_docker.py
symphony/node/runner_exec.py
symphony/transport/__init__.py
symphony/transport/grpc_client.py
symphony/transport/grpc_server.py
symphony/transport/security.py
symphony/util/__init__.py
symphony/util/backoff.py
symphony/util/time.py
symphony/util/usage.py
symphony/util/resource_monitoring/cpu.py
symphony/util/resource_monitoring/disk.py
symphony/util/resource_monitoring/models.py
symphony/util/resource_monitoring/monitor.py
symphony/util/resource_monitoring/nvidia.py
symphony/util/resource_monitoring/ram.py
symphony/util/resource_monitoring/utils.py
symphony/v1/__init__.py
symphony/v1/protocol_pb2.py
symphony/v1/protocol_pb2_grpc.py
symphony_orchestra-1.0.0b3.dist-info/licenses/LICENSE
symphony_orchestra-1.0.0b3.dist-info/METADATA
symphony_orchestra-1.0.0b3.dist-info/WHEEL
symphony_orchestra-1.0.0b3.dist-info/entry_points.txt
symphony_orchestra-1.0.0b3.dist-info/top_level.txt
symphony_orchestra-1.0.0b3.dist-info/RECORD
