Metadata-Version: 2.4
Name: symphony-orchestra
Version: 1.0.0b3
Summary: Lightweight container and job orchestrator
License: Apache-2.0
Project-URL: Homepage, https://github.com/ttheew/symphony
Project-URL: Source, https://github.com/ttheew/symphony
Project-URL: Issues, https://github.com/ttheew/symphony/issues
Project-URL: Documentation, https://github.com/ttheew/symphony#readme
Requires-Python: >=3.11
License-File: LICENSE
Requires-Dist: aiosqlite==0.22.1
Requires-Dist: fastapi==0.128.0
Requires-Dist: grpcio==1.76.0
Requires-Dist: orjson==3.11.5
Requires-Dist: pydantic==2.12.5
Requires-Dist: PyYAML==6.0.3
Requires-Dist: uvicorn==0.40.0
Requires-Dist: cryptography==44.0.0
Requires-Dist: nvidia-ml-py3==7.352.0
Requires-Dist: autoflake==2.3.1
Requires-Dist: black==25.12.0
Requires-Dist: grpcio-tools==1.76.0
Requires-Dist: isort==7.0.0
Requires-Dist: pyflakes==3.4.0
Requires-Dist: click==8.3.1
Requires-Dist: packaging==25.0
Requires-Dist: pathspec==0.12.1
Requires-Dist: platformdirs==4.5.1
Requires-Dist: mypy_extensions==1.1.0
Requires-Dist: pytokens==0.3.0
Requires-Dist: loguru==0.7.3
Dynamic: license-file
